indicative/__init__.py
indicative/adapters.py
indicative/collection.py
indicative/constants.py
indicative/datas.py
indicative/enums.py
indicative/history.py
indicative/mixins.py
indicative/protocols.py
indicative/resampler.py
indicative/types.py
indicative/indicators/__init__.py
indicative/indicators/adx.py
indicative/indicators/bbands.py
indicative/indicators/ema.py
indicative/indicators/macd.py
indicative/indicators/rsi.py
indicative/indicators/sma.py
indicative/indicators/stoch.py
indicative_py-0.0.1.dist-info/LICENSE
indicative_py-0.0.1.dist-info/METADATA
indicative_py-0.0.1.dist-info/WHEEL
indicative_py-0.0.1.dist-info/top_level.txt
indicative_py-0.0.1.dist-info/RECORD
