Metadata-Version: 2.1
Name: indicative-py
Version: 0.0.1
Summary: Pipeline-Oriented Technical Analysis Library
Author: Kachain Fuangsung
Author-email: kachain.f@outlook.com
License: MIT License
Classifier: Programming Language :: Python :: 3
Classifier: License :: OSI Approved :: MIT License
Requires-Python: >=3.12
License-File: LICENSE
Requires-Dist: numpy<3,>=2
Requires-Dist: pandas<3,>=2
Requires-Dist: TA-Lib<1,>=0.6
Requires-Dist: multimethod<3,>=2
Requires-Dist: pydantic<3,>=2
